pcf8574_interface/__init__.py
pcf8574_interface/pcf8574_interface.py
pcf8574_interface/pcf8574_interface_api.py
pcf8574_interface/pcf8574_pool.py
pcf8574_interface-1.1.0.dist-info/METADATA
pcf8574_interface-1.1.0.dist-info/WHEEL
pcf8574_interface-1.1.0.dist-info/licenses/LICENSE
pcf8574_interface-1.1.0.dist-info/RECORD
