Metadata-Version: 2.4
Name: pcf8574_interface
Version: 1.1.0
Summary: This package is a wrapper around the original PCF8574 library, providing enhanced functionality such as input/output value inversion, pin number reversal, value overrides, and integration with a custom API for client notifications.
Project-URL: Repository, https://codeberg.org/Foerderverein_DresdnerParkeisenbahn_eV/pcf8574_interface
Author-email: Timo Klinge <kl.timo@outlook.de>
License-Expression: MIT
License-File: LICENSE
Classifier: Operating System :: OS Independent
Classifier: Programming Language :: Python :: 3
Requires-Python: >=3.6
Requires-Dist: pcf8574-simulation
Provides-Extra: hardware
Requires-Dist: pcf8574; extra == 'hardware'
